indala_decoder.py
indala_decoder-1.0.8.dist-info/LICENSE
indala_decoder-1.0.8.dist-info/METADATA
indala_decoder-1.0.8.dist-info/WHEEL
indala_decoder-1.0.8.dist-info/top_level.txt
indala_decoder-1.0.8.dist-info/RECORD
