Metadata-Version: 2.1
Name: indala-decoder
Version: 1.0.8
Summary: A Python library for decoding 32-bit Indala26 codes into facility code and card numbers, and vice versa
Author: Logan Nommensen
Author-email: Logan Nommensen <logan.nommensen@gmail.com>
Project-URL: Homepage, https://github.com/muzak23/indala26-decoder
Project-URL: Issues, https://github.com/muzak23/indala26-decoder/issues
Keywords: Indala,Indala26,RFID,Indala keycard
Classifier: Programming Language :: Python :: 3
Classifier: License :: OSI Approved :: GNU General Public License v3 (GPLv3)
Classifier: Operating System :: OS Independent
Classifier: Topic :: Security
Requires-Python: >=3.8
License-File: LICENSE
